<?xml version = '1.0' encoding = 'UTF-8'?>
<Diagram class="oracle.dbtools.crest.swingui.relational.DPVRelational" name="Relational_1(2)" id="ACF269C3-779D-0A5A-26CD-D3C814E91541">
<createdBy>asus</createdBy>
<modifiedBy>asus</modifiedBy>
<createdTime>2019-05-07 11:44:52 UTC</createdTime>
<autoRoute>false</autoRoute>
<boxInbox>true</boxInbox>
<showLegend>false</showLegend>
<showLabels>false</showLabels>
<showRelAttributes>false</showRelAttributes>
<gridEnabled>false</gridEnabled>
<showGrid>false</showGrid>
<diagramColor>-1</diagramColor>
<display>false</display>
<notation>1</notation>
<objectViews>
<OView class="oracle.dbtools.crest.swingui.relational.TVTable" oid="11CED844-86BD-F31F-AAF0-EBC347404F76" otype="Table" vid="C5C9B79A-9CD3-A078-477E-FC369F32D04E">
<hideElementsInCurrentOnly>false</hideElementsInCurrentOnly>
<bounds x="1050" y="427" width="278" height="96"/>
</OView>
<OView class="oracle.dbtools.crest.swingui.relational.TVTable" oid="1D3BA560-4A88-6550-5827-F07EAC7B67F5" otype="Table" vid="716B852C-AA89-73DA-A44C-9B410AA9B635">
<hideElementsInCurrentOnly>false</hideElementsInCurrentOnly>
<bounds x="1050" y="295" width="332" height="96"/>
</OView>
<OView class="oracle.dbtools.crest.swingui.relational.TVTable" oid="1F5A3795-E2F6-7A01-8EEC-346524732104" otype="Table" vid="619D34BE-C79B-0713-0912-80AACB4AB9B2">
<hideElementsInCurrentOnly>false</hideElementsInCurrentOnly>
<bounds x="1119" y="7" width="248" height="124"/>
</OView>
<OView class="oracle.dbtools.crest.swingui.relational.TVTable" oid="2157C9AA-F25A-28A8-63AA-25F7784EF970" otype="Table" vid="489883A5-14EF-D61C-CC9A-4C1EA4D16338">
<hideElementsInCurrentOnly>false</hideElementsInCurrentOnly>
<bounds x="386" y="279" width="295" height="172"/>
</OView>
<OView class="oracle.dbtools.crest.swingui.relational.TVTable" oid="22B542E7-9A89-94C8-A65B-D491AF5773BD" otype="Table" vid="15B823E2-CA83-3EE0-8FDD-74BAE0757539">
<hideElementsInCurrentOnly>false</hideElementsInCurrentOnly>
<bounds x="1403" y="170" width="170" height="110"/>
</OView>
<OView class="oracle.dbtools.crest.swingui.relational.TVTable" oid="2BAA0FA1-2037-CC86-CC15-B51ABBAC3779" otype="Table" vid="0054CA3C-BAE9-CCF1-4C1C-C0149FD1E1F0">
<hideElementsInCurrentOnly>false</hideElementsInCurrentOnly>
<bounds x="733" y="165" width="259" height="159"/>
</OView>
<OView class="oracle.dbtools.crest.swingui.relational.TVTable" oid="2CCA6202-9412-C687-7FF8-4B2E33D38BD1" otype="Table" vid="524F8019-26E8-A566-0C1F-74FF097DE351">
<hideElementsInCurrentOnly>false</hideElementsInCurrentOnly>
<bounds x="1056" y="165" width="325" height="121"/>
</OView>
<OView class="oracle.dbtools.crest.swingui.relational.TVTable" oid="660266AF-A665-17D5-3640-0B3DA0E94A6A" otype="Table" vid="8E70A7AD-4BA6-9FAC-FAA7-E3082BD736B1">
<hideElementsInCurrentOnly>false</hideElementsInCurrentOnly>
<bounds x="139" y="147" width="355" height="115"/>
</OView>
<OView class="oracle.dbtools.crest.swingui.relational.TVTable" oid="8B925F5D-AA29-7AD7-A5DD-A92A5502A73E" otype="Table" vid="7E861B64-40D3-7255-3949-218C59674D8C">
<hideElementsInCurrentOnly>false</hideElementsInCurrentOnly>
<bounds x="222" y="491" width="199" height="104"/>
</OView>
<OView class="oracle.dbtools.crest.swingui.relational.TVTable" oid="A0D6BB93-CB99-A394-DEFF-A98B39E3B8D9" otype="Table" vid="A8EFEE2D-DAB9-9C19-943A-62F99986C044">
<hideElementsInCurrentOnly>false</hideElementsInCurrentOnly>
<bounds x="716" y="420" width="268" height="91"/>
</OView>
<OView class="oracle.dbtools.crest.swingui.relational.TVTable" oid="B49FFAC5-900A-DBD3-FC67-1A051960F42B" otype="Table" vid="B9CF3B33-BCCD-0FF1-E4B2-3B844297A509">
<hideElementsInCurrentOnly>false</hideElementsInCurrentOnly>
<bounds x="96" y="284" width="250" height="117"/>
</OView>
<OView class="oracle.dbtools.crest.swingui.relational.TVTable" oid="DF1F2B64-C3F7-3DAD-8036-FCE5E700A85C" otype="Table" vid="772D4820-78B2-1E8C-EE96-52A16ECCA174">
<hideElementsInCurrentOnly>false</hideElementsInCurrentOnly>
<bounds x="435" y="5" width="225" height="93"/>
</OView>
<OView class="oracle.dbtools.crest.swingui.relational.TVTable" oid="FEC8800A-5D37-E581-9CAA-41ECE92985F1" otype="Table" vid="0F9D5A4D-7593-088D-1837-113C84072399">
<hideElementsInCurrentOnly>false</hideElementsInCurrentOnly>
<bounds x="756" y="0" width="310" height="149"/>
</OView>
</objectViews>
<connectors>
<Connector class="oracle.dbtools.crest.swingui.relational.TVFKRelation" oid="13AD7540-EE80-FD97-79A1-8A35CCA39ACC" otype="FKIndexAssociation" vid_source="772D4820-78B2-1E8C-EE96-52A16ECCA174" vid_target="0054CA3C-BAE9-CCF1-4C1C-C0149FD1E1F0">
<hideElementsInCurrentOnly>false</hideElementsInCurrentOnly>
<backgroundColor>-16777216</backgroundColor>
<lineWidth>1</lineWidth>
<points>
<point x="623" y="98"/>
<point x="733" y="165"/>
</points>
</Connector>
<Connector class="oracle.dbtools.crest.swingui.relational.TVFKRelation" oid="15FCEC8A-5D8C-4109-B7C3-7E023E2D5DDC" otype="FKIndexAssociation" vid_source="0054CA3C-BAE9-CCF1-4C1C-C0149FD1E1F0" vid_target="C5C9B79A-9CD3-A078-477E-FC369F32D04E">
<hideElementsInCurrentOnly>false</hideElementsInCurrentOnly>
<backgroundColor>-16777216</backgroundColor>
<lineWidth>1</lineWidth>
<points>
<point x="975" y="324"/>
<point x="1121" y="427"/>
</points>
</Connector>
<Connector class="oracle.dbtools.crest.swingui.relational.TVFKRelation" oid="1AAB6682-2118-FC3C-FC32-410335FC884A" otype="FKIndexAssociation" vid_source="15B823E2-CA83-3EE0-8FDD-74BAE0757539" vid_target="524F8019-26E8-A566-0C1F-74FF097DE351">
<hideElementsInCurrentOnly>false</hideElementsInCurrentOnly>
<backgroundColor>-16777216</backgroundColor>
<lineWidth>1</lineWidth>
<points>
<point x="1403" y="225"/>
<point x="1381" y="225"/>
</points>
</Connector>
<Connector class="oracle.dbtools.crest.swingui.relational.TVFKRelation" oid="370B1DD3-59EC-FC40-7002-71CD603DB3FF" otype="FKIndexAssociation" vid_source="619D34BE-C79B-0713-0912-80AACB4AB9B2" vid_target="0054CA3C-BAE9-CCF1-4C1C-C0149FD1E1F0">
<hideElementsInCurrentOnly>false</hideElementsInCurrentOnly>
<backgroundColor>-16777216</backgroundColor>
<lineWidth>1</lineWidth>
<points>
<point x="1119" y="126"/>
<point x="992" y="184"/>
</points>
</Connector>
<Connector class="oracle.dbtools.crest.swingui.relational.TVFKRelation" oid="6F885129-7C67-1FAB-BA0F-2C0D283BC177" otype="FKIndexAssociation" vid_source="0054CA3C-BAE9-CCF1-4C1C-C0149FD1E1F0" vid_target="8E70A7AD-4BA6-9FAC-FAA7-E3082BD736B1">
<hideElementsInCurrentOnly>false</hideElementsInCurrentOnly>
<backgroundColor>-16777216</backgroundColor>
<lineWidth>1</lineWidth>
<points>
<point x="733" y="198"/>
<point x="494" y="198"/>
</points>
</Connector>
<Connector class="oracle.dbtools.crest.swingui.relational.TVFKRelation" oid="747A63C9-EA36-0825-DCB5-EA4B5A0B64DA" otype="FKIndexAssociation" vid_source="B9CF3B33-BCCD-0FF1-E4B2-3B844297A509" vid_target="489883A5-14EF-D61C-CC9A-4C1EA4D16338">
<hideElementsInCurrentOnly>false</hideElementsInCurrentOnly>
<backgroundColor>-16777216</backgroundColor>
<lineWidth>1</lineWidth>
<points>
<point x="346" y="342"/>
<point x="386" y="342"/>
</points>
</Connector>
<Connector class="oracle.dbtools.crest.swingui.relational.TVFKRelation" oid="9CC5903D-E1AA-55CA-6A88-2863A925FDCF" otype="FKIndexAssociation" vid_source="619D34BE-C79B-0713-0912-80AACB4AB9B2" vid_target="0F9D5A4D-7593-088D-1837-113C84072399">
<hideElementsInCurrentOnly>false</hideElementsInCurrentOnly>
<backgroundColor>-16777216</backgroundColor>
<lineWidth>1</lineWidth>
<points>
<point x="1119" y="69"/>
<point x="1066" y="69"/>
</points>
</Connector>
<Connector class="oracle.dbtools.crest.swingui.relational.TVFKRelation" oid="9E43C691-118D-0C9D-545D-C2FB9963733B" otype="FKIndexAssociation" vid_source="772D4820-78B2-1E8C-EE96-52A16ECCA174" vid_target="8E70A7AD-4BA6-9FAC-FAA7-E3082BD736B1">
<hideElementsInCurrentOnly>false</hideElementsInCurrentOnly>
<backgroundColor>-16777216</backgroundColor>
<lineWidth>1</lineWidth>
<points>
<point x="464" y="98"/>
<point x="464" y="147"/>
</points>
</Connector>
<Connector class="oracle.dbtools.crest.swingui.relational.TVFKRelation" oid="A4F454F8-E5FF-E068-943D-14A3A6BCED9B" otype="FKIndexAssociation" vid_source="0054CA3C-BAE9-CCF1-4C1C-C0149FD1E1F0" vid_target="489883A5-14EF-D61C-CC9A-4C1EA4D16338">
<hideElementsInCurrentOnly>false</hideElementsInCurrentOnly>
<backgroundColor>-16777216</backgroundColor>
<lineWidth>1</lineWidth>
<points>
<point x="733" y="301"/>
<point x="681" y="301"/>
</points>
</Connector>
<Connector class="oracle.dbtools.crest.swingui.relational.TVFKRelation" oid="C07E6958-67A1-4604-6B08-E46DFD6C3931" otype="FKIndexAssociation" vid_source="0054CA3C-BAE9-CCF1-4C1C-C0149FD1E1F0" vid_target="524F8019-26E8-A566-0C1F-74FF097DE351">
<hideElementsInCurrentOnly>false</hideElementsInCurrentOnly>
<backgroundColor>-16777216</backgroundColor>
<lineWidth>1</lineWidth>
<points>
<point x="992" y="225"/>
<point x="1056" y="225"/>
</points>
</Connector>
<Connector class="oracle.dbtools.crest.swingui.relational.TVFKRelation" oid="C279F9BD-5FF5-1ADC-F403-2F6999F9B31E" otype="FKIndexAssociation" vid_source="772D4820-78B2-1E8C-EE96-52A16ECCA174" vid_target="0F9D5A4D-7593-088D-1837-113C84072399">
<hideElementsInCurrentOnly>false</hideElementsInCurrentOnly>
<backgroundColor>-16777216</backgroundColor>
<lineWidth>1</lineWidth>
<points>
<point x="660" y="51"/>
<point x="756" y="51"/>
</points>
</Connector>
<Connector class="oracle.dbtools.crest.swingui.relational.TVFKRelation" oid="E3760D67-EA32-8E87-DD65-7438AAB012A6" otype="FKIndexAssociation" vid_source="0054CA3C-BAE9-CCF1-4C1C-C0149FD1E1F0" vid_target="A8EFEE2D-DAB9-9C19-943A-62F99986C044">
<hideElementsInCurrentOnly>false</hideElementsInCurrentOnly>
<backgroundColor>-16777216</backgroundColor>
<lineWidth>1</lineWidth>
<points>
<point x="858" y="324"/>
<point x="858" y="420"/>
</points>
</Connector>
<Connector class="oracle.dbtools.crest.swingui.relational.TVFKRelation" oid="EEDFD78F-CE12-4AEA-3AD6-4AE6345DF9B3" otype="FKIndexAssociation" vid_source="0054CA3C-BAE9-CCF1-4C1C-C0149FD1E1F0" vid_target="716B852C-AA89-73DA-A44C-9B410AA9B635">
<hideElementsInCurrentOnly>false</hideElementsInCurrentOnly>
<backgroundColor>-16777216</backgroundColor>
<lineWidth>1</lineWidth>
<points>
<point x="992" y="309"/>
<point x="1050" y="309"/>
</points>
</Connector>
</connectors>
</Diagram>